xlsxObject/SheetData.py
xlsxObject/XlsxObject.py
xlsxObject/__init__.py
xslxObject-0.3.0.dist-info/LICENSE
xslxObject-0.3.0.dist-info/METADATA
xslxObject-0.3.0.dist-info/WHEEL
xslxObject-0.3.0.dist-info/top_level.txt
xslxObject-0.3.0.dist-info/RECORD
