Metadata-Version: 2.1
Name: xslxObject
Version: 0.3.0
Summary: Object approach to xslx files
Home-page: UNKNOWN
Author: Samuel Baker
Author-email: samuelbaker.researcher@gmail.com
Maintainer: Samuel Baker
Maintainer-email: samuelbaker.researcher@gmail.com
License: MIT
Download-URL: https://github.com/sbaker-dev/xslxObject
Platform: UNKNOWN
Classifier: Programming Language :: Python :: 3.7
Classifier: Programming Language :: Python :: 3.8
Classifier: License :: OSI Approved :: MIT License
Requires-Python: >=3.6
Requires-Dist: miscSupports
Requires-Dist: openpyxl
